mongo
mongo.py
mongo_cmd-0.0.0.2.dist-info/METADATA
mongo_cmd-0.0.0.2.dist-info/WHEEL
mongo_cmd-0.0.0.2.dist-info/RECORD
